[{ "seconds": 0, "temperature" : 19.0}
,{ "seconds": 1, "temperature" : 19.0}
,{ "seconds": 2, "temperature" : 19.0}
,{ "seconds": 3, "temperature" : 19.0}
,{ "seconds": 4, "temperature" : 19.0}
,{ "seconds": 5, "temperature" : 19.0}
,{ "seconds": 6, "temperature" : 19.0}
,{ "seconds": 7, "temperature" : 19.0}
,{ "seconds": 8, "temperature" : 19.0}
,{ "seconds": 9, "temperature" : 19.0}
,{ "seconds": 10, "temperature" : 19.0}
,{ "seconds": 11, "temperature" : 19.0}
,{ "seconds": 12, "temperature" : 19.0}
,{ "seconds": 13, "temperature" : 19.0}
,{ "seconds": 14, "temperature" : 19.0}
]